archub/__init__.py
archub/cmdline.py
archub/config.py
archub/core.py
archub/commands/__init__.py
archub/commands/branch.py
archub/commands/issues.py
archub/commands/members.py
archub/commands/pullrequest.py
archub/commands/push.py
archub/commands/task.py
archub/commands/todo.py
archub-1.0.0a8.data/scripts/ah
archub-1.0.0a8.data/scripts/archub
archub-1.0.0a8.dist-info/METADATA
archub-1.0.0a8.dist-info/RECORD
archub-1.0.0a8.dist-info/WHEEL
archub-1.0.0a8.dist-info/top_level.txt
