Metadata-Version: 2.1
Name: archub
Version: 1.0.0a8
Summary: UNKNOWN
Home-page: https://github.com/rfldong/archub
Author: Don Grote
Author-email: dgrote@refirmlabs.com
License: UNKNOWN
Platform: UNKNOWN
Classifier: Programming Language :: Python
Classifier: Programming Language :: Python :: 3
Classifier: Development Status :: 2 - Pre-Alpha
Classifier: Environment :: Console
Classifier: Intended Audience :: Developers
Classifier: Operating System :: POSIX :: Linux
Classifier: License :: OSI Approved :: Apache Software License
Classifier: Natural Language :: English
Classifier: Topic :: Software Development
Classifier: Topic :: Software Development :: Bug Tracking
Classifier: Topic :: Software Development :: Version Control :: Git
Requires-Dist: requests
Requires-Dist: pygithub
Requires-Dist: gitpython
